{"dependencies":[{"name":"C:\\Users\\Matt Development\\Desktop\\int-app-dev\\javascript-basics\\exercises\\npm-modules\\package.json","includedInParent":true,"mtime":1689215978116},{"name":"C:\\Users\\Matt Development\\Desktop\\int-app-dev\\javascript-basics\\exercises\\npm-modules\\node_modules\\faker\\package.json","includedInParent":true,"mtime":1688099252676}],"generated":{"js":"module[\"exports\"] = [\n\n];\n","map":{"mappings":[{"source":"node_modules\\faker\\lib\\locales\\az\\address\\state.js","original":{"line":1,"column":0},"generated":{"line":1,"column":0}},{"source":"node_modules\\faker\\lib\\locales\\az\\address\\state.js","original":{"line":2,"column":0},"generated":{"line":2,"column":0}},{"source":"node_modules\\faker\\lib\\locales\\az\\address\\state.js","original":{"line":3,"column":0},"generated":{"line":3,"column":0}},{"source":"node_modules\\faker\\lib\\locales\\az\\address\\state.js","original":{"line":4,"column":0},"generated":{"line":4,"column":0}}],"sources":{"node_modules\\faker\\lib\\locales\\az\\address\\state.js":"module[\"exports\"] = [\n\n];\n"},"lineCount":4}},"hash":"1b4499542714b6b5c1cf6efff841a03a","cacheData":{"env":{}}}