{"dependencies":[],"generated":{"js":"module[\"exports\"] = [\n  \"San\",\n  \"Borgo\",\n  \"Sesto\",\n  \"Quarto\",\n  \"Settimo\"\n];\n","map":{"mappings":[{"source":"node_modules\\faker\\lib\\locales\\it\\address\\city_prefix.js","original":{"line":1,"column":0},"generated":{"line":1,"column":0}},{"source":"node_modules\\faker\\lib\\locales\\it\\address\\city_prefix.js","original":{"line":2,"column":0},"generated":{"line":2,"column":0}},{"source":"node_modules\\faker\\lib\\locales\\it\\address\\city_prefix.js","original":{"line":3,"column":0},"generated":{"line":3,"column":0}},{"source":"node_modules\\faker\\lib\\locales\\it\\address\\city_prefix.js","original":{"line":4,"column":0},"generated":{"line":4,"column":0}},{"source":"node_modules\\faker\\lib\\locales\\it\\address\\city_prefix.js","original":{"line":5,"column":0},"generated":{"line":5,"column":0}},{"source":"node_modules\\faker\\lib\\locales\\it\\address\\city_prefix.js","original":{"line":6,"column":0},"generated":{"line":6,"column":0}},{"source":"node_modules\\faker\\lib\\locales\\it\\address\\city_prefix.js","original":{"line":7,"column":0},"generated":{"line":7,"column":0}},{"source":"node_modules\\faker\\lib\\locales\\it\\address\\city_prefix.js","original":{"line":8,"column":0},"generated":{"line":8,"column":0}}],"sources":{"node_modules\\faker\\lib\\locales\\it\\address\\city_prefix.js":"module[\"exports\"] = [\n  \"San\",\n  \"Borgo\",\n  \"Sesto\",\n  \"Quarto\",\n  \"Settimo\"\n];\n"},"lineCount":8}},"hash":"144164c5bdcb0a090a79a3161305e909","cacheData":{"env":{}}}