{"dependencies":[],"generated":{"js":"module[\"exports\"] = [\n  \"#{city_prefix}\"\n];\n","map":{"mappings":[{"source":"node_modules\\faker\\lib\\locales\\es_MX\\address\\city.js","original":{"line":1,"column":0},"generated":{"line":1,"column":0}},{"source":"node_modules\\faker\\lib\\locales\\es_MX\\address\\city.js","original":{"line":2,"column":0},"generated":{"line":2,"column":0}},{"source":"node_modules\\faker\\lib\\locales\\es_MX\\address\\city.js","original":{"line":3,"column":0},"generated":{"line":3,"column":0}},{"source":"node_modules\\faker\\lib\\locales\\es_MX\\address\\city.js","original":{"line":4,"column":0},"generated":{"line":4,"column":0}}],"sources":{"node_modules\\faker\\lib\\locales\\es_MX\\address\\city.js":"module[\"exports\"] = [\n  \"#{city_prefix}\"\n];\n"},"lineCount":4}},"hash":"ac07bfb0f2ef75ba4ff364d9c2dea05f","cacheData":{"env":{}}}